duration_parser/__init__.py
duration_parser/_parsing.py
duration_parser/py.typed
duration_parser-1.0.1.dist-info/LICENSE
duration_parser-1.0.1.dist-info/METADATA
duration_parser-1.0.1.dist-info/WHEEL
duration_parser-1.0.1.dist-info/top_level.txt
duration_parser-1.0.1.dist-info/RECORD
