Metadata-Version: 2.1
Name: duration-parser
Version: 1.0.1
Summary: Duration parser.
Home-page: https://github.com/adriansahlman/duration-parser
Author: Adrian Sahlman
Author-email: adrian.sahlman@gmail.com
License: MIT
Keywords: duration parse parser parsing
Platform: UNKNOWN
Classifier: Programming Language :: Python :: 3
Classifier: Programming Language :: Python :: 3 :: Only
Classifier: Intended Audience :: Developers
Requires-Python: >=3.7
